boucing_square/__init__.py
boucing_square/game.py
bouncing_square-0.1.dist-info/METADATA
bouncing_square-0.1.dist-info/WHEEL
bouncing_square-0.1.dist-info/entry_points.txt
bouncing_square-0.1.dist-info/top_level.txt
bouncing_square-0.1.dist-info/RECORD
